LICENSE
MANIFEST.in
README.md
requirements.txt
setup.py
brainmodels/__init__.py
brainmodels.egg-info/PKG-INFO
brainmodels.egg-info/SOURCES.txt
brainmodels.egg-info/dependency_links.txt
brainmodels.egg-info/requires.txt
brainmodels.egg-info/top_level.txt
brainmodels/channels/Ca_channels.py
brainmodels/channels/Ih_channels.py
brainmodels/channels/KCa_channels.py
brainmodels/channels/K_channels.py
brainmodels/channels/Na_channels.py
brainmodels/channels/__init__.py
brainmodels/channels/base.py
brainmodels/channels/other_channels.py
brainmodels/neurons/AdExIF.py
brainmodels/neurons/AdQuaIF.py
brainmodels/neurons/ExpIF.py
brainmodels/neurons/FHN.py
brainmodels/neurons/GIF.py
brainmodels/neurons/HH.py
brainmodels/neurons/HindmarshRose.py
brainmodels/neurons/Izhikevich.py
brainmodels/neurons/LIF.py
brainmodels/neurons/MorrisLecar.py
brainmodels/neurons/QuaIF.py
brainmodels/neurons/__init__.py
brainmodels/neurons/base.py
brainmodels/neurons/tests/__init__.py
brainmodels/synapses/AMPA.py
brainmodels/synapses/GABAa.py
brainmodels/synapses/NMDA.py
brainmodels/synapses/STP.py
brainmodels/synapses/__init__.py
brainmodels/synapses/alpha.py
brainmodels/synapses/base.py
brainmodels/synapses/dual_exp.py
brainmodels/synapses/exponential.py
brainmodels/synapses/voltage_jump.py
brainmodels/synapses/tests/__init__.py